akili/__init__.py
akili/assistants/__init__.py
akili/assistants/client.py
akili/client.py
akili/configs/__init__.py
akili/configs/client.py
akili/core/__init__.py
akili/core/api_error.py
akili/core/client_wrapper.py
akili/core/datetime_utils.py
akili/core/file.py
akili/core/http_client.py
akili/core/jsonable_encoder.py
akili/core/pydantic_utilities.py
akili/core/query_encoder.py
akili/core/remove_none_from_dict.py
akili/core/request_options.py
akili/core/serialization.py
akili/environment.py
akili/errors/__init__.py
akili/errors/unprocessable_entity_error.py
akili/py.typed
akili/runs/__init__.py
akili/runs/client.py
akili/runs/types/__init__.py
akili/runs/types/score.py
akili/runs/types/value.py
akili/threads/__init__.py
akili/threads/client.py
akili/types/__init__.py
akili/types/assistant.py
akili/types/assistant_payload.py
akili/types/assistant_version.py
akili/types/callbacks.py
akili/types/checkpoint.py
akili/types/content.py
akili/types/create_run_payload.py
akili/types/http_validation_error.py
akili/types/human_message.py
akili/types/human_message_content_item.py
akili/types/input.py
akili/types/interrupt.py
akili/types/model_provider.py
akili/types/provider.py
akili/types/runnable_config.py
akili/types/thread.py
akili/types/thread_put_request.py
akili/types/thread_state.py
akili/types/thread_task.py
akili/types/tool_config.py
akili/types/tool_registry_base.py
akili/types/validation_error.py
akili/types/validation_error_loc_item.py
akili/types/values.py
akili/version.py
akili_python-0.0.9.dist-info/METADATA
akili_python-0.0.9.dist-info/WHEEL
akili_python-0.0.9.dist-info/RECORD
